biobabel/__init__.py
biobabel/biodata.py
biobabel/io.py
biobabel/load_acq.py
biobabel/load_bdf.py
biobabel/load_bramsbiobox.py
biobabel/load_edf.py
biobabel/load_genericcsv.py
biobabel/load_hdphysio5.py
biobabel/load_lsl.py
biobabel/load_opensignals.py
biobabel/load_teensyecg.py
biobabel/viewer.py
biobabel-1.0.4.dist-info/LICENSE
biobabel-1.0.4.dist-info/METADATA
biobabel-1.0.4.dist-info/WHEEL
biobabel-1.0.4.dist-info/entry_points.txt
biobabel-1.0.4.dist-info/top_level.txt
biobabel-1.0.4.dist-info/RECORD
