Metadata-Version: 2.1
Name: biobabel
Version: 1.0.4
Summary: Python wrapper for reading major bio/physiology data formats (e.g. ECG, PPG, EDA) into a unified accessible interface
Author-email: Floris van Vugt <ftvanvugt@gmail.com>
Project-URL: Homepage, https://github.com/florisvanvugt/biobabel
Classifier: Programming Language :: Python :: 3
Classifier: Operating System :: OS Independent
Requires-Python: >=3.7
License-File: LICENSE
Requires-Dist: h5py
Requires-Dist: numpy
Requires-Dist: pyxdf
Requires-Dist: matplotlib
Requires-Dist: bioread
Requires-Dist: opensignalsreader
Requires-Dist: pandas
Requires-Dist: pyedflib
Requires-Dist: scipy
Provides-Extra: bdf
Requires-Dist: pybdf ; extra == 'bdf'
